odoo/addons/__init__.py
odoo/addons/l10n_fr_pos_cert/__init__.py
odoo/addons/l10n_fr_pos_cert/__manifest__.py
odoo/addons/l10n_fr_pos_cert/data/pos_inalterability.xml
odoo/addons/l10n_fr_pos_cert/models/__init__.py
odoo/addons/l10n_fr_pos_cert/models/account_bank_statement.py
odoo/addons/l10n_fr_pos_cert/models/pos.py
odoo/addons/l10n_fr_pos_cert/models/res_company.py
odoo/addons/l10n_fr_pos_cert/static/description/icon.png
odoo/addons/l10n_fr_pos_cert/views/account_views.xml
odoo/addons/point_of_sale/README.md
odoo/addons/point_of_sale/__init__.py
odoo/addons/point_of_sale/__manifest__.py
odoo/addons/point_of_sale/controllers/__init__.py
odoo/addons/point_of_sale/controllers/main.py
odoo/addons/point_of_sale/controllers/web_editor.py
odoo/addons/point_of_sale/data/default_barcode_patterns.xml
odoo/addons/point_of_sale/data/point_of_sale_data.xml
odoo/addons/point_of_sale/data/point_of_sale_demo.xml
odoo/addons/point_of_sale/doc/barcode_test_sheet.pdf
odoo/addons/point_of_sale/doc/barcode_test_sheet.svg
odoo/addons/point_of_sale/doc/barcode_test_sheet2.svg
odoo/addons/point_of_sale/doc/barcode_test_sheet4.pdf
odoo/addons/point_of_sale/doc/barcode_test_sheet4.svg
odoo/addons/point_of_sale/doc/barcode_test_sheet_new.svg
odoo/addons/point_of_sale/i18n/af.po
odoo/addons/point_of_sale/i18n/am.po
odoo/addons/point_of_sale/i18n/ar.po
odoo/addons/point_of_sale/i18n/bg.po
odoo/addons/point_of_sale/i18n/bs.po
odoo/addons/point_of_sale/i18n/ca.po
odoo/addons/point_of_sale/i18n/cs.po
odoo/addons/point_of_sale/i18n/da.po
odoo/addons/point_of_sale/i18n/de.po
odoo/addons/point_of_sale/i18n/el.po
odoo/addons/point_of_sale/i18n/es.po
odoo/addons/point_of_sale/i18n/es_BO.po
odoo/addons/point_of_sale/i18n/es_CL.po
odoo/addons/point_of_sale/i18n/es_CO.po
odoo/addons/point_of_sale/i18n/es_CR.po
odoo/addons/point_of_sale/i18n/es_PE.po
odoo/addons/point_of_sale/i18n/es_PY.po
odoo/addons/point_of_sale/i18n/es_VE.po
odoo/addons/point_of_sale/i18n/et.po
odoo/addons/point_of_sale/i18n/eu.po
odooku_odoo_point_of_sale-11.0.7.dist-info/LICENSE
odooku_odoo_point_of_sale-11.0.7.dist-info/METADATA
odooku_odoo_point_of_sale-11.0.7.dist-info/WHEEL
odooku_odoo_point_of_sale-11.0.7.dist-info/top_level.txt
odooku_odoo_point_of_sale-11.0.7.dist-info/RECORD
